stannetflow/__init__.py
stannetflow/analyze_functions.py
stannetflow/preprocess.py
stannetflow/artificial/__init__.py
stannetflow/artificial/datamaker.py
stannetflow/synthesizers/__init__.py
stannetflow/synthesizers/nets.py
stannetflow/synthesizers/stan.py
stannetflow-0.0.1.dist-info/LICENSE
stannetflow-0.0.1.dist-info/METADATA
stannetflow-0.0.1.dist-info/WHEEL
stannetflow-0.0.1.dist-info/top_level.txt
stannetflow-0.0.1.dist-info/RECORD
