Metadata-Version: 2.1
Name: stannetflow
Version: 0.0.1
Summary: top-level package for netflow-stan
Home-page: https://github.com/ShengzheXu/stan
Author: Shengzhe Xu
Author-email: shengzx@vt.edu
License: UNKNOWN
Platform: UNKNOWN
Classifier: Programming Language :: Python :: 3
Classifier: License :: OSI Approved :: MIT License
Classifier: Operating System :: OS Independent
Requires-Dist: numpy
Requires-Dist: pandas
Requires-Dist: scikit-learn
Requires-Dist: matplotlib
Requires-Dist: torch
